qmlmch/__init__.py
qmlmch/modulo.py
qmlmch-0.1.8.dist-info/METADATA
qmlmch-0.1.8.dist-info/WHEEL
qmlmch-0.1.8.dist-info/top_level.txt
qmlmch-0.1.8.dist-info/RECORD
