Metadata-Version: 2.1
Name: qmlmch
Version: 0.1.8
Summary: library ML
Author: Luciano M
Author-email: luciano.munoz1@udea.edu.co
License: MIT
Requires-Python: >=3.10.12
Requires-Dist: numpy
Requires-Dist: plotly
Requires-Dist: scipy
Requires-Dist: kaleido
